{
	"configurations" : 
	[
		{
			"directories" : 
			[
				{
					"build" : ".",
					"childIndexes" : 
					[
						1
					],
					"hasInstallRule" : true,
					"jsonFile" : "directory-.-Debug-d0094a50bb2071803777.json",
					"minimumCMakeVersion" : 
					{
						"string" : "3.15"
					},
					"projectIndex" : 0,
					"source" : ".",
					"targetIndexes" : 
					[
						0,
						2,
						3,
						5
					]
				},
				{
					"build" : "include/glfw",
					"childIndexes" : 
					[
						2
					],
					"hasInstallRule" : true,
					"jsonFile" : "directory-include.glfw-Debug-49d19b1e81bd04c279ee.json",
					"minimumCMakeVersion" : 
					{
						"string" : "3.16"
					},
					"parentIndex" : 0,
					"projectIndex" : 1,
					"source" : "include/glfw",
					"targetIndexes" : 
					[
						1,
						6
					]
				},
				{
					"build" : "include/glfw/src",
					"hasInstallRule" : true,
					"jsonFile" : "directory-include.glfw.src-Debug-68e5ee05a1dcb42e505f.json",
					"minimumCMakeVersion" : 
					{
						"string" : "3.16"
					},
					"parentIndex" : 1,
					"projectIndex" : 1,
					"source" : "include/glfw/src",
					"targetIndexes" : 
					[
						4,
						7
					]
				}
			],
			"name" : "Debug",
			"projects" : 
			[
				{
					"childIndexes" : 
					[
						1
					],
					"directoryIndexes" : 
					[
						0
					],
					"name" : "FolderSort",
					"targetIndexes" : 
					[
						0,
						2,
						3,
						5
					]
				},
				{
					"directoryIndexes" : 
					[
						1,
						2
					],
					"name" : "GLFW",
					"parentIndex" : 0,
					"targetIndexes" : 
					[
						1,
						4,
						6,
						7
					]
				}
			],
			"targets" : 
			[
				{
					"directoryIndex" : 0,
					"id" : "ALL_BUILD::@6890427a1f51a3e7e1df",
					"jsonFile" : "target-ALL_BUILD-Debug-f5bd9179a08fd4f59068.json",
					"name" : "ALL_BUILD",
					"projectIndex" : 0
				},
				{
					"directoryIndex" : 1,
					"id" : "ALL_BUILD::@11f96312bf0093c46211",
					"jsonFile" : "target-ALL_BUILD-Debug-c2d19dd7f0e2eea7479f.json",
					"name" : "ALL_BUILD",
					"projectIndex" : 1
				},
				{
					"directoryIndex" : 0,
					"id" : "FolderSort::@6890427a1f51a3e7e1df",
					"jsonFile" : "target-FolderSort-Debug-cf782757cc01b9c56404.json",
					"name" : "FolderSort",
					"projectIndex" : 0
				},
				{
					"directoryIndex" : 0,
					"id" : "ZERO_CHECK::@6890427a1f51a3e7e1df",
					"jsonFile" : "target-ZERO_CHECK-Debug-7a4dab6a156427c700a7.json",
					"name" : "ZERO_CHECK",
					"projectIndex" : 0
				},
				{
					"directoryIndex" : 2,
					"id" : "glfw::@7cf4cdf8cc575720cdf7",
					"jsonFile" : "target-glfw-Debug-825a49149b1521ce2768.json",
					"name" : "glfw",
					"projectIndex" : 1
				},
				{
					"directoryIndex" : 0,
					"id" : "imgui::@6890427a1f51a3e7e1df",
					"jsonFile" : "target-imgui-Debug-7ebfc2014c7ce6774d67.json",
					"name" : "imgui",
					"projectIndex" : 0
				},
				{
					"directoryIndex" : 1,
					"id" : "uninstall::@11f96312bf0093c46211",
					"jsonFile" : "target-uninstall-Debug-964d473ffdbb6ec25750.json",
					"name" : "uninstall",
					"projectIndex" : 1
				},
				{
					"directoryIndex" : 2,
					"id" : "update_mappings::@7cf4cdf8cc575720cdf7",
					"jsonFile" : "target-update_mappings-Debug-13c0c69b07f2d3218127.json",
					"name" : "update_mappings",
					"projectIndex" : 1
				}
			]
		},
		{
			"directories" : 
			[
				{
					"build" : ".",
					"childIndexes" : 
					[
						1
					],
					"hasInstallRule" : true,
					"jsonFile" : "directory-.-Release-d0094a50bb2071803777.json",
					"minimumCMakeVersion" : 
					{
						"string" : "3.15"
					},
					"projectIndex" : 0,
					"source" : ".",
					"targetIndexes" : 
					[
						0,
						2,
						3,
						5
					]
				},
				{
					"build" : "include/glfw",
					"childIndexes" : 
					[
						2
					],
					"hasInstallRule" : true,
					"jsonFile" : "directory-include.glfw-Release-49d19b1e81bd04c279ee.json",
					"minimumCMakeVersion" : 
					{
						"string" : "3.16"
					},
					"parentIndex" : 0,
					"projectIndex" : 1,
					"source" : "include/glfw",
					"targetIndexes" : 
					[
						1,
						6
					]
				},
				{
					"build" : "include/glfw/src",
					"hasInstallRule" : true,
					"jsonFile" : "directory-include.glfw.src-Release-7cbba0c6dad2124cf173.json",
					"minimumCMakeVersion" : 
					{
						"string" : "3.16"
					},
					"parentIndex" : 1,
					"projectIndex" : 1,
					"source" : "include/glfw/src",
					"targetIndexes" : 
					[
						4,
						7
					]
				}
			],
			"name" : "Release",
			"projects" : 
			[
				{
					"childIndexes" : 
					[
						1
					],
					"directoryIndexes" : 
					[
						0
					],
					"name" : "FolderSort",
					"targetIndexes" : 
					[
						0,
						2,
						3,
						5
					]
				},
				{
					"directoryIndexes" : 
					[
						1,
						2
					],
					"name" : "GLFW",
					"parentIndex" : 0,
					"targetIndexes" : 
					[
						1,
						4,
						6,
						7
					]
				}
			],
			"targets" : 
			[
				{
					"directoryIndex" : 0,
					"id" : "ALL_BUILD::@6890427a1f51a3e7e1df",
					"jsonFile" : "target-ALL_BUILD-Release-f5bd9179a08fd4f59068.json",
					"name" : "ALL_BUILD",
					"projectIndex" : 0
				},
				{
					"directoryIndex" : 1,
					"id" : "ALL_BUILD::@11f96312bf0093c46211",
					"jsonFile" : "target-ALL_BUILD-Release-c2d19dd7f0e2eea7479f.json",
					"name" : "ALL_BUILD",
					"projectIndex" : 1
				},
				{
					"directoryIndex" : 0,
					"id" : "FolderSort::@6890427a1f51a3e7e1df",
					"jsonFile" : "target-FolderSort-Release-086902fea4b4bf7e5446.json",
					"name" : "FolderSort",
					"projectIndex" : 0
				},
				{
					"directoryIndex" : 0,
					"id" : "ZERO_CHECK::@6890427a1f51a3e7e1df",
					"jsonFile" : "target-ZERO_CHECK-Release-7a4dab6a156427c700a7.json",
					"name" : "ZERO_CHECK",
					"projectIndex" : 0
				},
				{
					"directoryIndex" : 2,
					"id" : "glfw::@7cf4cdf8cc575720cdf7",
					"jsonFile" : "target-glfw-Release-e2187c04e663fb6df1bc.json",
					"name" : "glfw",
					"projectIndex" : 1
				},
				{
					"directoryIndex" : 0,
					"id" : "imgui::@6890427a1f51a3e7e1df",
					"jsonFile" : "target-imgui-Release-227c5291475f844655fd.json",
					"name" : "imgui",
					"projectIndex" : 0
				},
				{
					"directoryIndex" : 1,
					"id" : "uninstall::@11f96312bf0093c46211",
					"jsonFile" : "target-uninstall-Release-964d473ffdbb6ec25750.json",
					"name" : "uninstall",
					"projectIndex" : 1
				},
				{
					"directoryIndex" : 2,
					"id" : "update_mappings::@7cf4cdf8cc575720cdf7",
					"jsonFile" : "target-update_mappings-Release-13c0c69b07f2d3218127.json",
					"name" : "update_mappings",
					"projectIndex" : 1
				}
			]
		},
		{
			"directories" : 
			[
				{
					"build" : ".",
					"childIndexes" : 
					[
						1
					],
					"hasInstallRule" : true,
					"jsonFile" : "directory-.-MinSizeRel-d0094a50bb2071803777.json",
					"minimumCMakeVersion" : 
					{
						"string" : "3.15"
					},
					"projectIndex" : 0,
					"source" : ".",
					"targetIndexes" : 
					[
						0,
						2,
						3,
						5
					]
				},
				{
					"build" : "include/glfw",
					"childIndexes" : 
					[
						2
					],
					"hasInstallRule" : true,
					"jsonFile" : "directory-include.glfw-MinSizeRel-49d19b1e81bd04c279ee.json",
					"minimumCMakeVersion" : 
					{
						"string" : "3.16"
					},
					"parentIndex" : 0,
					"projectIndex" : 1,
					"source" : "include/glfw",
					"targetIndexes" : 
					[
						1,
						6
					]
				},
				{
					"build" : "include/glfw/src",
					"hasInstallRule" : true,
					"jsonFile" : "directory-include.glfw.src-MinSizeRel-63a31779ac03f842aa52.json",
					"minimumCMakeVersion" : 
					{
						"string" : "3.16"
					},
					"parentIndex" : 1,
					"projectIndex" : 1,
					"source" : "include/glfw/src",
					"targetIndexes" : 
					[
						4,
						7
					]
				}
			],
			"name" : "MinSizeRel",
			"projects" : 
			[
				{
					"childIndexes" : 
					[
						1
					],
					"directoryIndexes" : 
					[
						0
					],
					"name" : "FolderSort",
					"targetIndexes" : 
					[
						0,
						2,
						3,
						5
					]
				},
				{
					"directoryIndexes" : 
					[
						1,
						2
					],
					"name" : "GLFW",
					"parentIndex" : 0,
					"targetIndexes" : 
					[
						1,
						4,
						6,
						7
					]
				}
			],
			"targets" : 
			[
				{
					"directoryIndex" : 0,
					"id" : "ALL_BUILD::@6890427a1f51a3e7e1df",
					"jsonFile" : "target-ALL_BUILD-MinSizeRel-f5bd9179a08fd4f59068.json",
					"name" : "ALL_BUILD",
					"projectIndex" : 0
				},
				{
					"directoryIndex" : 1,
					"id" : "ALL_BUILD::@11f96312bf0093c46211",
					"jsonFile" : "target-ALL_BUILD-MinSizeRel-c2d19dd7f0e2eea7479f.json",
					"name" : "ALL_BUILD",
					"projectIndex" : 1
				},
				{
					"directoryIndex" : 0,
					"id" : "FolderSort::@6890427a1f51a3e7e1df",
					"jsonFile" : "target-FolderSort-MinSizeRel-e46f564dbeb40ace242a.json",
					"name" : "FolderSort",
					"projectIndex" : 0
				},
				{
					"directoryIndex" : 0,
					"id" : "ZERO_CHECK::@6890427a1f51a3e7e1df",
					"jsonFile" : "target-ZERO_CHECK-MinSizeRel-7a4dab6a156427c700a7.json",
					"name" : "ZERO_CHECK",
					"projectIndex" : 0
				},
				{
					"directoryIndex" : 2,
					"id" : "glfw::@7cf4cdf8cc575720cdf7",
					"jsonFile" : "target-glfw-MinSizeRel-22fe62dbd2bf7418d802.json",
					"name" : "glfw",
					"projectIndex" : 1
				},
				{
					"directoryIndex" : 0,
					"id" : "imgui::@6890427a1f51a3e7e1df",
					"jsonFile" : "target-imgui-MinSizeRel-08c231e98220ccb351cf.json",
					"name" : "imgui",
					"projectIndex" : 0
				},
				{
					"directoryIndex" : 1,
					"id" : "uninstall::@11f96312bf0093c46211",
					"jsonFile" : "target-uninstall-MinSizeRel-964d473ffdbb6ec25750.json",
					"name" : "uninstall",
					"projectIndex" : 1
				},
				{
					"directoryIndex" : 2,
					"id" : "update_mappings::@7cf4cdf8cc575720cdf7",
					"jsonFile" : "target-update_mappings-MinSizeRel-13c0c69b07f2d3218127.json",
					"name" : "update_mappings",
					"projectIndex" : 1
				}
			]
		},
		{
			"directories" : 
			[
				{
					"build" : ".",
					"childIndexes" : 
					[
						1
					],
					"hasInstallRule" : true,
					"jsonFile" : "directory-.-RelWithDebInfo-d0094a50bb2071803777.json",
					"minimumCMakeVersion" : 
					{
						"string" : "3.15"
					},
					"projectIndex" : 0,
					"source" : ".",
					"targetIndexes" : 
					[
						0,
						2,
						3,
						5
					]
				},
				{
					"build" : "include/glfw",
					"childIndexes" : 
					[
						2
					],
					"hasInstallRule" : true,
					"jsonFile" : "directory-include.glfw-RelWithDebInfo-49d19b1e81bd04c279ee.json",
					"minimumCMakeVersion" : 
					{
						"string" : "3.16"
					},
					"parentIndex" : 0,
					"projectIndex" : 1,
					"source" : "include/glfw",
					"targetIndexes" : 
					[
						1,
						6
					]
				},
				{
					"build" : "include/glfw/src",
					"hasInstallRule" : true,
					"jsonFile" : "directory-include.glfw.src-RelWithDebInfo-a1b73d3f0d956709011d.json",
					"minimumCMakeVersion" : 
					{
						"string" : "3.16"
					},
					"parentIndex" : 1,
					"projectIndex" : 1,
					"source" : "include/glfw/src",
					"targetIndexes" : 
					[
						4,
						7
					]
				}
			],
			"name" : "RelWithDebInfo",
			"projects" : 
			[
				{
					"childIndexes" : 
					[
						1
					],
					"directoryIndexes" : 
					[
						0
					],
					"name" : "FolderSort",
					"targetIndexes" : 
					[
						0,
						2,
						3,
						5
					]
				},
				{
					"directoryIndexes" : 
					[
						1,
						2
					],
					"name" : "GLFW",
					"parentIndex" : 0,
					"targetIndexes" : 
					[
						1,
						4,
						6,
						7
					]
				}
			],
			"targets" : 
			[
				{
					"directoryIndex" : 0,
					"id" : "ALL_BUILD::@6890427a1f51a3e7e1df",
					"jsonFile" : "target-ALL_BUILD-RelWithDebInfo-f5bd9179a08fd4f59068.json",
					"name" : "ALL_BUILD",
					"projectIndex" : 0
				},
				{
					"directoryIndex" : 1,
					"id" : "ALL_BUILD::@11f96312bf0093c46211",
					"jsonFile" : "target-ALL_BUILD-RelWithDebInfo-c2d19dd7f0e2eea7479f.json",
					"name" : "ALL_BUILD",
					"projectIndex" : 1
				},
				{
					"directoryIndex" : 0,
					"id" : "FolderSort::@6890427a1f51a3e7e1df",
					"jsonFile" : "target-FolderSort-RelWithDebInfo-1fee2e6f394b80f312f0.json",
					"name" : "FolderSort",
					"projectIndex" : 0
				},
				{
					"directoryIndex" : 0,
					"id" : "ZERO_CHECK::@6890427a1f51a3e7e1df",
					"jsonFile" : "target-ZERO_CHECK-RelWithDebInfo-7a4dab6a156427c700a7.json",
					"name" : "ZERO_CHECK",
					"projectIndex" : 0
				},
				{
					"directoryIndex" : 2,
					"id" : "glfw::@7cf4cdf8cc575720cdf7",
					"jsonFile" : "target-glfw-RelWithDebInfo-1bb224129e9fb4739076.json",
					"name" : "glfw",
					"projectIndex" : 1
				},
				{
					"directoryIndex" : 0,
					"id" : "imgui::@6890427a1f51a3e7e1df",
					"jsonFile" : "target-imgui-RelWithDebInfo-20c7c961c8f95a71e8a7.json",
					"name" : "imgui",
					"projectIndex" : 0
				},
				{
					"directoryIndex" : 1,
					"id" : "uninstall::@11f96312bf0093c46211",
					"jsonFile" : "target-uninstall-RelWithDebInfo-964d473ffdbb6ec25750.json",
					"name" : "uninstall",
					"projectIndex" : 1
				},
				{
					"directoryIndex" : 2,
					"id" : "update_mappings::@7cf4cdf8cc575720cdf7",
					"jsonFile" : "target-update_mappings-RelWithDebInfo-13c0c69b07f2d3218127.json",
					"name" : "update_mappings",
					"projectIndex" : 1
				}
			]
		}
	],
	"kind" : "codemodel",
	"paths" : 
	{
		"build" : "E:/Projects/FolderSort/build",
		"source" : "E:/Projects/FolderSort"
	},
	"version" : 
	{
		"major" : 2,
		"minor" : 7
	}
}
